neural_network_lib/__init__.py
neural_network_lib/activations.py
neural_network_lib/layers.py
neural_network_lib/losses.py
neural_network_lib/network.py
neural_network_lib/network_save_and_load.py
neural_network_lib/train.py
neural_network_lib/utils.py
neural_network_lib-0.4.0.dist-info/METADATA
neural_network_lib-0.4.0.dist-info/WHEEL
neural_network_lib-0.4.0.dist-info/top_level.txt
neural_network_lib-0.4.0.dist-info/RECORD
