Metadata-Version: 2.4
Name: neural-network-lib
Version: 0.4.0
Summary: Легковесная библиотека для создания и обучения нейронных сетей с GPU-ускорением
Author: Тихонов Иван
Author-email: tihonovivan737@gmail.com
Requires-Python: >=3.6
Dynamic: author
Dynamic: author-email
Dynamic: description
Dynamic: description-content-type
Dynamic: requires-python
Dynamic: summary
